jedai_core/__init__.py
jedai_core/common/__init__.py
jedai_core/generate_social_content/__init__.py
jedai_core/generate_social_content/admin.py
jedai_core/generate_social_content/agents.py
jedai_core/generate_social_content/apps.py
jedai_core/generate_social_content/exceptions.py
jedai_core/generate_social_content/models.py
jedai_core/generate_social_content/tasks.py
jedai_core/generate_social_content/utils.py
jedai_core/generate_social_content/views.py
jedai_core/generate_social_content/migrations/0001_initial.py
jedai_core/generate_social_content/migrations/__init__.py
jedai_core/generate_social_content/resources/company_data.json
jedai_core/generate_social_content/resources/general_rules.md
jedai_core-0.1.0.dist-info/licenses/LICENSE
jedai_core-0.1.0.dist-info/WHEEL
jedai_core-0.1.0.dist-info/METADATA
jedai_core-0.1.0.dist-info/RECORD
