Metadata-Version: 2.4
Name: jedai-core
Version: 0.1.0
Summary: Biblioteca core com módulos AI, com diversos casos de uso, e Common
Author-email: Ruan Heleno da Rocha Vieira <ruan.empreenderop@gmail.com>
Requires-Python: >=3.8
License-Expression: MIT
Classifier: Programming Language :: Python :: 3
Classifier: Operating System :: OS Independent
License-File: LICENSE
Requires-Dist: openai==1.54.1
Requires-Dist: langchain==0.3.7
Requires-Dist: langchain_openai==0.2.6
Requires-Dist: langchain-core==0.3.15
Requires-Dist: crewai==0.76.9
Requires-Dist: crewai-tools==0.13.4
Requires-Dist: httpx==0.27.2
Requires-Dist: beautifulsoup4==4.12.3
Requires-Dist: pkginfo==1.12.1
Project-URL: Homepage, https://github.com/cads-ai/core
